ckanext/__init__.py
ckanext/duo/__init__.py
ckanext/duo/plugin.py
ckanext/duo/signals.py
ckanext/duo/dataset_templates/package/snippets/package_basic_fields.html
ckanext/duo/group_templates/group/snippets/group_form.html
ckanext/duo/organization_templates/organization/snippets/organization_form.html
ckanext/duo/schemas/group.json
ckanext/duo/schemas/organization.json
ckanext/duo/tests/__init__.py
ckanext/duo/tests/test_plugin.py
ckanext_duo-0.1.2.post1.dist-info/LICENSE
ckanext_duo-0.1.2.post1.dist-info/METADATA
ckanext_duo-0.1.2.post1.dist-info/WHEEL
ckanext_duo-0.1.2.post1.dist-info/entry_points.txt
ckanext_duo-0.1.2.post1.dist-info/top_level.txt
ckanext_duo-0.1.2.post1.dist-info/RECORD
